src/chainthon/__init__.py
src/chainthon/app.py
src/chainthon/cli.py
src/chainthon/logger.py
src/chainthon/version.py
src/chainthon/core/__init__.py
src/chainthon/utils/__init__.py
src/chainthon/utils/nest_event.py
src/tests/__init__.py
src/tests/test_cli.py
chainthon-0.1.2.dist-info/METADATA
chainthon-0.1.2.dist-info/WHEEL
chainthon-0.1.2.dist-info/entry_points.txt
chainthon-0.1.2.dist-info/RECORD
