Metadata-Version: 2.3
Name: chainthon
Version: 0.1.2
Summary: A Python library for building chatbots and conversational applications
Author-email: rontom <rontomai@gmail.com>
License: Apache License, Version 2.0
Requires-Python: >=3.8
Requires-Dist: click>=8.0.0
Requires-Dist: fastapi>=0.68.0
Requires-Dist: pydantic>=2.0.0
Requires-Dist: uvicorn>=0.15.0
Provides-Extra: dev
Requires-Dist: black>=21.0; extra == 'dev'
Requires-Dist: isort>=5.0; extra == 'dev'
Requires-Dist: mypy>=0.900; extra == 'dev'
Requires-Dist: pytest-asyncio>=0.14.0; extra == 'dev'
Requires-Dist: pytest>=6.0; extra == 'dev'
Requires-Dist: ruff>=0.1.0; extra == 'dev'
